chainlib/chain.py
chainlib/hash.py
chainlib/status.py
chainlib/eth/address.py
chainlib/eth/block.py
chainlib/eth/connection.py
chainlib/eth/constant.py
chainlib/eth/encoding.py
chainlib/eth/erc20.py
chainlib/eth/error.py
chainlib/eth/gas.py
chainlib/eth/hash.py
chainlib/eth/nonce.py
chainlib/eth/rpc.py
chainlib/eth/tx.py
chainlib/eth/runnable/__init__.py
chainlib/eth/runnable/balance.py
chainlib/eth/runnable/checksum.py
chainlib/eth/runnable/decode.py
chainlib/eth/runnable/gas.py
chainlib/eth/runnable/get.py
chainlib/eth/runnable/subscribe.py
chainlib/eth/runnable/transfer.py
cic_tools/eth/address.py
cic_tools/eth/connection.py
cic_tools/eth/constant.py
cic_tools/eth/error.py
cic_tools/eth/gas.py
cic_tools/eth/hash.py
cic_tools/eth/method.py
cic_tools/eth/nonce.py
cic_tools/eth/tx.py
cic_tools/eth/runnable/__init__.py
cic_tools/eth/runnable/balance.py
cic_tools/eth/runnable/checksum.py
cic_tools/eth/runnable/decode.py
cic_tools/eth/runnable/gas.py
cic_tools/eth/runnable/subscribe.py
chainlib-0.0.1a19.dist-info/LICENSE.txt
chainlib-0.0.1a19.dist-info/METADATA
chainlib-0.0.1a19.dist-info/WHEEL
chainlib-0.0.1a19.dist-info/entry_points.txt
chainlib-0.0.1a19.dist-info/top_level.txt
chainlib-0.0.1a19.dist-info/RECORD
